minimaldb/__init__.py
minimaldb-1.2.dist-info/LICENSE
minimaldb-1.2.dist-info/METADATA
minimaldb-1.2.dist-info/WHEEL
minimaldb-1.2.dist-info/top_level.txt
minimaldb-1.2.dist-info/RECORD
