Metadata-Version: 2.1
Name: minimaldb
Version: 1.2
Summary: Minimalistic document oriented database.
Home-page: http://github.com/ZAZPRO/minimaldb
Author: Daniil Mira
Author-email: daniilmira@gmail.com
License: UNKNOWN
Platform: UNKNOWN
Classifier: Programming Language :: Python :: 3
Classifier: License :: OSI Approved :: MIT License
Classifier: Operating System :: OS Independent
